labor/__init__.py
labor/api.py
labor/banner.txt
labor/beautify.py
labor/cli.py
labor/config.py
labor/controllers/login.py
labor/date_utils.py
labor/enums/api.py
labor/services/login.py
labor/test.py
labor/utils/alert.py
labor/utils/config.py
labor/utils/file_helper.py
labor-0.2.2.dist-info/entry_points.txt
labor-0.2.2.dist-info/LICENSE
labor-0.2.2.dist-info/WHEEL
labor-0.2.2.dist-info/METADATA
labor-0.2.2.dist-info/RECORD
