Metadata-Version: 2.1
Name: labor
Version: 0.2.2
Summary: getLabor cli
Home-page: https://github.com/gabssanto/labor-cli
License: MIT
Author: Gabriel Santo
Author-email: gabssanto@users.noreply.github.com
Requires-Python: >=3.8,<4.0
Classifier: License :: OSI Approved :: MIT License
Classifier: Programming Language :: Python :: 3
Classifier: Programming Language :: Python :: 3.10
Classifier: Programming Language :: Python :: 3.8
Classifier: Programming Language :: Python :: 3.9
Requires-Dist: click (>=8.1.3,<9.0.0)
Requires-Dist: colorama (>=0.4.3,<0.5.0)
Requires-Dist: httpx (>=0.23.0,<0.24.0)
Requires-Dist: rich (>=12.4.4,<13.0.0)
Requires-Dist: termcolor (>=1.1.0,<2.0.0)
